MANIFEST.in
README.md
setup.cfg
setup.py
metrics_tracker_client/__init__.py
metrics_tracker_client/metrics.py
metrics_tracker_client.egg-info/PKG-INFO
metrics_tracker_client.egg-info/SOURCES.txt
metrics_tracker_client.egg-info/dependency_links.txt
metrics_tracker_client.egg-info/requires.txt
metrics_tracker_client.egg-info/top_level.txt