Metadata-Version: 1.1
Name: metrics-tracker-client
Version: 1.0.9
Summary: Python client for the deployment tracker
Home-page: https://github.com/IBM/metrics-collector-client-python
Author: Jake Peyser, Tommy Li
Author-email: jepeyser@us.ibm.com, Tommy.chaoping.li@ibm.com
License: Apache-2.0
Keywords: demos samples metrics
Platform: UNKNOWN
Classifier: Development Status :: 5 - Production/Stable
Classifier: Intended Audience :: Developers
Classifier: Topic :: Software Development :: Libraries :: Python Modules
Classifier: License :: OSI Approved :: Apache Software License
Classifier: Programming Language :: Python :: 2.7
Classifier: Programming Language :: Python :: 3.3
Classifier: Programming Language :: Python :: 3.4
Classifier: Programming Language :: Python :: 3.5
